validkit/__init__.py
validkit/v.py
validkit/validator.py
validkit_py-1.0.2.dist-info/METADATA
validkit_py-1.0.2.dist-info/WHEEL
validkit_py-1.0.2.dist-info/licenses/LICENSE
validkit_py-1.0.2.dist-info/RECORD
