Metadata-Version: 2.4
Name: validkit-py
Version: 1.0.2
Summary: A simple and powerful validation library for Python.
Project-URL: Homepage, https://github.com/disnana/ValidKit
Author: disnana
License: MIT
License-File: LICENSE
Classifier: License :: OSI Approved :: MIT License
Classifier: Operating System :: OS Independent
Classifier: Programming Language :: Python :: 3
Classifier: Topic :: Software Development :: Libraries :: Python Modules
Requires-Python: >=3.9
